genut_py/__init__.py
genut_py/format.py
genut_py/genut.py
genut_py/state.py
genut_py/trace.py
genut_py-0.1.3.dist-info/LICENSE
genut_py-0.1.3.dist-info/METADATA
genut_py-0.1.3.dist-info/WHEEL
genut_py-0.1.3.dist-info/RECORD
