Metadata-Version: 2.1
Name: genut-py
Version: 0.1.3
Summary: 
License: MIT
Author: Eiichiro Sato
Author-email: gasinsato@example.com
Requires-Python: >=3.10,<4.0
Classifier: License :: OSI Approved :: MIT License
Classifier: Programming Language :: Python :: 3
Classifier: Programming Language :: Python :: 3.10
Classifier: Programming Language :: Python :: 3.11
Requires-Dist: coverage (==7.3.2)
